{
  "WebCountyRecord": [
    {
      "CountyId": 290,
      "UtilityId": null,
      "CountyName": "Alachua",
      "CountyState": null,
      "CountyStatus": "#45715D",
      "OutageCount": 5705,
      "CustomerCount": 133068
    },
    {
      "CountyId": 291,
      "UtilityId": null,
      "CountyName": "Baker",
      "CountyState": null,
      "CountyStatus": "#316771",
      "OutageCount": 370,
      "CustomerCount": 12292
    },
    {
      "CountyId": 292,
      "UtilityId": null,
      "CountyName": "Bay",
      "CountyState": null,
      "CountyStatus": "#004FA2",
      "OutageCount": 0,
      "CustomerCount": 116615
    },
    {
      "CountyId": 293,
      "UtilityId": null,
      "CountyName": "Bradford",
      "CountyState": null,
      "CountyStatus": "#125890",
      "OutageCount": 119,
      "CustomerCount": 10439
    },
    {
      "CountyId": 294,
      "UtilityId": null,
      "CountyName": "Brevard",
      "CountyState": null,
      "CountyStatus": "#B16F00",
      "OutageCount": 70451,
      "CustomerCount": 330448
    },
    {
      "CountyId": 295,
      "UtilityId": null,
      "CountyName": "Broward",
      "CountyState": null,
      "CountyStatus": "#08539A",
      "OutageCount": 4872,
      "CustomerCount": 963625
    },
    {
      "CountyId": 296,
      "UtilityId": null,
      "CountyName": "Charlotte",
      "CountyState": null,
      "CountyStatus": "#640C02",
      "OutageCount": 116828,
      "CustomerCount": 127498
    },
    {
      "CountyId": 297,
      "UtilityId": null,
      "CountyName": "Citrus",
      "CountyState": null,
      "CountyStatus": "#527750",
      "OutageCount": 4721,
      "CustomerCount": 93569
    },
    {
      "CountyId": 298,
      "UtilityId": null,
      "CountyName": "Clay",
      "CountyState": null,
      "CountyStatus": "#48735A",
      "OutageCount": 4275,
      "CustomerCount": 95582
    },
    {
      "CountyId": 299,
      "UtilityId": null,
      "CountyName": "Collier",
      "CountyState": null,
      "CountyStatus": "#800F01",
      "OutageCount": 202857,
      "CustomerCount": 262833
    },
    {
      "CountyId": 300,
      "UtilityId": null,
      "CountyName": "Columbia",
      "CountyState": null,
      "CountyStatus": "#85901D",
      "OutageCount": 2897,
      "CustomerCount": 35395
    },
    {
      "CountyId": 302,
      "UtilityId": null,
      "CountyName": "Dixie",
      "CountyState": null,
      "CountyStatus": "#0A5498",
      "OutageCount": 67,
      "CustomerCount": 10657
    },
    {
      "CountyId": 303,
      "UtilityId": null,
      "CountyName": "Duval",
      "CountyState": null,
      "CountyStatus": "#0B5497",
      "OutageCount": 3201,
      "CustomerCount": 476425
    },
    {
      "CountyId": 304,
      "UtilityId": null,
      "CountyName": "Flagler",
      "CountyState": null,
      "CountyStatus": "#A98700",
      "OutageCount": 10460,
      "CustomerCount": 66938
    },
    {
      "CountyId": 305,
      "UtilityId": null,
      "CountyName": "Franklin",
      "CountyState": null,
      "CountyStatus": "#004FA2",
      "OutageCount": 0,
      "CustomerCount": 11098
    },
    {
      "CountyId": 306,
      "UtilityId": null,
      "CountyName": "Gadsden",
      "CountyState": null,
      "CountyStatus": "#004FA2",
      "OutageCount": 2,
      "CustomerCount": 15318
    },
    {
      "CountyId": 307,
      "UtilityId": null,
      "CountyName": "Gilchrist",
      "CountyState": null,
      "CountyStatus": "#105792",
      "OutageCount": 99,
      "CustomerCount": 9842
    },
    {
      "CountyId": 308,
      "UtilityId": null,
      "CountyName": "Glades",
      "CountyState": null,
      "CountyStatus": "#7D0F01",
      "OutageCount": 5376,
      "CustomerCount": 6800
    },
    {
      "CountyId": 309,
      "UtilityId": null,
      "CountyName": "Gulf",
      "CountyState": null,
      "CountyStatus": "#004FA2",
      "OutageCount": 0,
      "CustomerCount": 11710
    },
    {
      "CountyId": 310,
      "UtilityId": null,
      "CountyName": "Hamilton",
      "CountyState": null,
      "CountyStatus": "#004FA2",
      "OutageCount": 0,
      "CustomerCount": 7137
    },
    {
      "CountyId": 311,
      "UtilityId": null,
      "CountyName": "Hardee",
      "CountyState": null,
      "CountyStatus": "#550A02",
      "OutageCount": 9504,
      "CustomerCount": 9544
    },
    {
      "CountyId": 312,
      "UtilityId": null,
      "CountyName": "Hendry",
      "CountyState": null,
      "CountyStatus": "#A31600",
      "OutageCount": 9203,
      "CustomerCount": 15770
    },
    {
      "CountyId": 313,
      "UtilityId": null,
      "CountyName": "Hernando",
      "CountyState": null,
      "CountyStatus": "#26627C",
      "OutageCount": 2403,
      "CustomerCount": 101184
    },
    {
      "CountyId": 314,
      "UtilityId": null,
      "CountyName": "Highlands",
      "CountyState": null,
      "CountyStatus": "#770E01",
      "OutageCount": 53633,
      "CustomerCount": 65368
    },
    {
      "CountyId": 315,
      "UtilityId": null,
      "CountyName": "Hillsborough",
      "CountyState": null,
      "CountyStatus": "#BA4700",
      "OutageCount": 217583,
      "CustomerCount": 673532
    },
    {
      "CountyId": 316,
      "UtilityId": null,
      "CountyName": "Indian River",
      "CountyState": null,
      "CountyStatus": "#B95600",
      "OutageCount": 27190,
      "CustomerCount": 99475
    },
    {
      "CountyId": 317,
      "UtilityId": null,
      "CountyName": "Jefferson",
      "CountyState": null,
      "CountyStatus": "#004FA2",
      "OutageCount": 0,
      "CustomerCount": 8683
    },
    {
      "CountyId": 318,
      "UtilityId": null,
      "CountyName": "Lafayette",
      "CountyState": null,
      "CountyStatus": "#004FA2",
      "OutageCount": 1,
      "CustomerCount": 4378
    },
    {
      "CountyId": 319,
      "UtilityId": null,
      "CountyName": "Lake",
      "CountyState": null,
      "CountyStatus": "#A88D00",
      "OutageCount": 24250,
      "CustomerCount": 169651
    },
    {
      "CountyId": 320,
      "UtilityId": null,
      "CountyName": "Lee",
      "CountyState": null,
      "CountyStatus": "#690C01",
      "OutageCount": 421247,
      "CustomerCount": 471806
    },
    {
      "CountyId": 321,
      "UtilityId": null,
      "CountyName": "Leon",
      "CountyState": null,
      "CountyStatus": "#004FA2",
      "OutageCount": 28,
      "CustomerCount": 131049
    },
    {
      "CountyId": 322,
      "UtilityId": null,
      "CountyName": "Levy",
      "CountyState": null,
      "CountyStatus": "#43705F",
      "OutageCount": 1020,
      "CustomerCount": 24810
    },
    {
      "CountyId": 323,
      "UtilityId": null,
      "CountyName": "Liberty",
      "CountyState": null,
      "CountyStatus": "#004FA2",
      "OutageCount": 1,
      "CustomerCount": 4173
    },
    {
      "CountyId": 324,
      "UtilityId": null,
      "CountyName": "Madison",
      "CountyState": null,
      "CountyStatus": "#004FA2",
      "OutageCount": 0,
      "CustomerCount": 11475
    },
    {
      "CountyId": 325,
      "UtilityId": null,
      "CountyName": "Manatee",
      "CountyState": null,
      "CountyStatus": "#921100",
      "OutageCount": 159765,
      "CustomerCount": 235081
    },
    {
      "CountyId": 326,
      "UtilityId": null,
      "CountyName": "Marion",
      "CountyState": null,
      "CountyStatus": "#416F61",
      "OutageCount": 8297,
      "CustomerCount": 208062
    },
    {
      "CountyId": 327,
      "UtilityId": null,
      "CountyName": "Martin",
      "CountyState": null,
      "CountyStatus": "#A98800",
      "OutageCount": 14680,
      "CustomerCount": 94710
    },
    {
      "CountyId": 328,
      "UtilityId": null,
      "CountyName": "Miami-dade",
      "CountyState": null,
      "CountyStatus": "#095399",
      "OutageCount": 6250,
      "CustomerCount": 1180070
    },
    {
      "CountyId": 329,
      "UtilityId": null,
      "CountyName": "Monroe",
      "CountyState": null,
      "CountyStatus": "#0A5498",
      "OutageCount": 586,
      "CustomerCount": 99765
    },
    {
      "CountyId": 330,
      "UtilityId": null,
      "CountyName": "Nassau",
      "CountyState": null,
      "CountyStatus": "#0B5597",
      "OutageCount": 362,
      "CustomerCount": 51188
    },
    {
      "CountyId": 331,
      "UtilityId": null,
      "CountyName": "Okeechobee",
      "CountyState": null,
      "CountyStatus": "#7B0E01",
      "OutageCount": 18409,
      "CustomerCount": 22938
    },
    {
      "CountyId": 332,
      "UtilityId": null,
      "CountyName": "Orange",
      "CountyState": null,
      "CountyStatus": "#B26A00",
      "OutageCount": 143119,
      "CustomerCount": 633110
    },
    {
      "CountyId": 333,
      "UtilityId": null,
      "CountyName": "Osceola",
      "CountyState": null,
      "CountyStatus": "#AD7D00",
      "OutageCount": 36383,
      "CustomerCount": 200164
    },
    {
      "CountyId": 334,
      "UtilityId": null,
      "CountyName": "Palm Beach",
      "CountyState": null,
      "CountyStatus": "#1D5D85",
      "OutageCount": 13590,
      "CustomerCount": 766020
    },
    {
      "CountyId": 335,
      "UtilityId": null,
      "CountyName": "Pasco",
      "CountyState": null,
      "CountyStatus": "#A88D00",
      "OutageCount": 43160,
      "CustomerCount": 302866
    },
    {
      "CountyId": 336,
      "UtilityId": null,
      "CountyName": "Pinellas",
      "CountyState": null,
      "CountyStatus": "#B94500",
      "OutageCount": 190419,
      "CustomerCount": 570938
    },
    {
      "CountyId": 337,
      "UtilityId": null,
      "CountyName": "Polk",
      "CountyState": null,
      "CountyStatus": "#A71F00",
      "OutageCount": 191087,
      "CustomerCount": 355057
    },
    {
      "CountyId": 338,
      "UtilityId": null,
      "CountyName": "Putnam",
      "CountyState": null,
      "CountyStatus": "#6E8534",
      "OutageCount": 2877,
      "CustomerCount": 42472
    },
    {
      "CountyId": 339,
      "UtilityId": null,
      "CountyName": "Sarasota",
      "CountyState": null,
      "CountyStatus": "#7E0F01",
      "OutageCount": 225500,
      "CustomerCount": 287123
    },
    {
      "CountyId": 340,
      "UtilityId": null,
      "CountyName": "Seminole",
      "CountyState": null,
      "CountyStatus": "#B94500",
      "OutageCount": 74738,
      "CustomerCount": 225139
    },
    {
      "CountyId": 342,
      "UtilityId": null,
      "CountyName": "St. Lucie",
      "CountyState": null,
      "CountyStatus": "#B85600",
      "OutageCount": 47449,
      "CustomerCount": 173837
    },
    {
      "CountyId": 343,
      "UtilityId": null,
      "CountyName": "Sumter",
      "CountyState": null,
      "CountyStatus": "#5B7C47",
      "OutageCount": 4791,
      "CustomerCount": 85441
    },
    {
      "CountyId": 344,
      "UtilityId": null,
      "CountyName": "Suwannee",
      "CountyState": null,
      "CountyStatus": "#05519D",
      "OutageCount": 70,
      "CustomerCount": 24343
    },
    {
      "CountyId": 345,
      "UtilityId": null,
      "CountyName": "Taylor",
      "CountyState": null,
      "CountyStatus": "#004FA2",
      "OutageCount": 0,
      "CustomerCount": 13694
    },
    {
      "CountyId": 346,
      "UtilityId": null,
      "CountyName": "Union",
      "CountyState": null,
      "CountyStatus": "#44705E",
      "OutageCount": 240,
      "CustomerCount": 5751
    },
    {
      "CountyId": 347,
      "UtilityId": null,
      "CountyName": "Unknown",
      "CountyState": null,
      "CountyStatus": "#AF7600",
      "OutageCount": 2798,
      "CustomerCount": 14078
    },
    {
      "CountyId": 348,
      "UtilityId": null,
      "CountyName": "Volusia",
      "CountyState": null,
      "CountyStatus": "#BB4900",
      "OutageCount": 95834,
      "CustomerCount": 310303
    },
    {
      "CountyId": 349,
      "UtilityId": null,
      "CountyName": "Wakulla",
      "CountyState": null,
      "CountyStatus": "#004FA2",
      "OutageCount": 0,
      "CustomerCount": 17457
    },
    {
      "CountyId": 2272,
      "UtilityId": null,
      "CountyName": "Escambia",
      "CountyState": null,
      "CountyStatus": "#004FA2",
      "OutageCount": 1,
      "CustomerCount": 157691
    },
    {
      "CountyId": 2273,
      "UtilityId": null,
      "CountyName": "Holmes",
      "CountyState": null,
      "CountyStatus": "#004FA2",
      "OutageCount": 0,
      "CustomerCount": 10665
    },
    {
      "CountyId": 2274,
      "UtilityId": null,
      "CountyName": "Jackson",
      "CountyState": null,
      "CountyStatus": "#004FA2",
      "OutageCount": 0,
      "CustomerCount": 33513
    },
    {
      "CountyId": 2275,
      "UtilityId": null,
      "CountyName": "Okaloosa",
      "CountyState": null,
      "CountyStatus": "#004FA2",
      "OutageCount": 0,
      "CustomerCount": 114532
    },
    {
      "CountyId": 2276,
      "UtilityId": null,
      "CountyName": "Santa Rosa",
      "CountyState": null,
      "CountyStatus": "#0250A0",
      "OutageCount": 91,
      "CustomerCount": 85032
    },
    {
      "CountyId": 2277,
      "UtilityId": null,
      "CountyName": "Walton",
      "CountyState": null,
      "CountyStatus": "#004FA2",
      "OutageCount": 0,
      "CustomerCount": 68943
    },
    {
      "CountyId": 2278,
      "UtilityId": null,
      "CountyName": "Washington",
      "CountyState": null,
      "CountyStatus": "#004FA2",
      "OutageCount": 0,
      "CustomerCount": 13325
    },
    {
      "CountyId": 2317,
      "UtilityId": null,
      "CountyName": "St. Johns",
      "CountyState": null,
      "CountyStatus": "#4F7653",
      "OutageCount": 6454,
      "CustomerCount": 132884
    },
    {
      "CountyId": 2340,
      "UtilityId": null,
      "CountyName": "Desoto",
      "CountyState": null,
      "CountyStatus": "#640C02",
      "OutageCount": 17198,
      "CustomerCount": 18739
    },
    {
      "CountyId": 2343,
      "UtilityId": null,
      "CountyName": "Calhoun",
      "CountyState": null,
      "CountyStatus": "#004FA2",
      "OutageCount": 0,
      "CustomerCount": 5479
    }
  ]
}
