{
  "WebCountyRecord": [
    {
      "CountyId": 290,
      "UtilityId": null,
      "CountyName": "Alachua",
      "CountyState": null,
      "CountyStatus": "#004FA2",
      "OutageCount": 0,
      "CustomerCount": 133293
    },
    {
      "CountyId": 291,
      "UtilityId": null,
      "CountyName": "Baker",
      "CountyState": null,
      "CountyStatus": "#004FA2",
      "OutageCount": 0,
      "CustomerCount": 12311
    },
    {
      "CountyId": 292,
      "UtilityId": null,
      "CountyName": "Bay",
      "CountyState": null,
      "CountyStatus": "#004FA2",
      "OutageCount": 4,
      "CustomerCount": 115985
    },
    {
      "CountyId": 293,
      "UtilityId": null,
      "CountyName": "Bradford",
      "CountyState": null,
      "CountyStatus": "#004FA2",
      "OutageCount": 0,
      "CustomerCount": 10471
    },
    {
      "CountyId": 294,
      "UtilityId": null,
      "CountyName": "Brevard",
      "CountyState": null,
      "CountyStatus": "#014FA1",
      "OutageCount": 190,
      "CustomerCount": 331317
    },
    {
      "CountyId": 295,
      "UtilityId": null,
      "CountyName": "Broward",
      "CountyState": null,
      "CountyStatus": "#004FA2",
      "OutageCount": 0,
      "CustomerCount": 963820
    },
    {
      "CountyId": 296,
      "UtilityId": null,
      "CountyName": "Charlotte",
      "CountyState": null,
      "CountyStatus": "#004FA2",
      "OutageCount": 0,
      "CustomerCount": 127280
    },
    {
      "CountyId": 297,
      "UtilityId": null,
      "CountyName": "Citrus",
      "CountyState": null,
      "CountyStatus": "#004FA2",
      "OutageCount": 0,
      "CustomerCount": 94000
    },
    {
      "CountyId": 298,
      "UtilityId": null,
      "CountyName": "Clay",
      "CountyState": null,
      "CountyStatus": "#004FA2",
      "OutageCount": 0,
      "CustomerCount": 96109
    },
    {
      "CountyId": 299,
      "UtilityId": null,
      "CountyName": "Collier",
      "CountyState": null,
      "CountyStatus": "#004FA2",
      "OutageCount": 0,
      "CustomerCount": 267535
    },
    {
      "CountyId": 300,
      "UtilityId": null,
      "CountyName": "Columbia",
      "CountyState": null,
      "CountyStatus": "#004FA2",
      "OutageCount": 0,
      "CustomerCount": 35406
    },
    {
      "CountyId": 302,
      "UtilityId": null,
      "CountyName": "Dixie",
      "CountyState": null,
      "CountyStatus": "#004FA2",
      "OutageCount": 0,
      "CustomerCount": 10659
    },
    {
      "CountyId": 303,
      "UtilityId": null,
      "CountyName": "Duval",
      "CountyState": null,
      "CountyStatus": "#004FA2",
      "OutageCount": 4,
      "CustomerCount": 478410
    },
    {
      "CountyId": 304,
      "UtilityId": null,
      "CountyName": "Flagler",
      "CountyState": null,
      "CountyStatus": "#004FA2",
      "OutageCount": 0,
      "CustomerCount": 67414
    },
    {
      "CountyId": 305,
      "UtilityId": null,
      "CountyName": "Franklin",
      "CountyState": null,
      "CountyStatus": "#004FA2",
      "OutageCount": 0,
      "CustomerCount": 11166
    },
    {
      "CountyId": 306,
      "UtilityId": null,
      "CountyName": "Gadsden",
      "CountyState": null,
      "CountyStatus": "#004FA2",
      "OutageCount": 0,
      "CustomerCount": 15357
    },
    {
      "CountyId": 307,
      "UtilityId": null,
      "CountyName": "Gilchrist",
      "CountyState": null,
      "CountyStatus": "#004FA2",
      "OutageCount": 0,
      "CustomerCount": 9848
    },
    {
      "CountyId": 308,
      "UtilityId": null,
      "CountyName": "Glades",
      "CountyState": null,
      "CountyStatus": "#004FA2",
      "OutageCount": 0,
      "CustomerCount": 6922
    },
    {
      "CountyId": 309,
      "UtilityId": null,
      "CountyName": "Gulf",
      "CountyState": null,
      "CountyStatus": "#004FA2",
      "OutageCount": 0,
      "CustomerCount": 11840
    },
    {
      "CountyId": 310,
      "UtilityId": null,
      "CountyName": "Hamilton",
      "CountyState": null,
      "CountyStatus": "#004FA2",
      "OutageCount": 0,
      "CustomerCount": 7128
    },
    {
      "CountyId": 311,
      "UtilityId": null,
      "CountyName": "Hardee",
      "CountyState": null,
      "CountyStatus": "#004FA2",
      "OutageCount": 0,
      "CustomerCount": 9524
    },
    {
      "CountyId": 312,
      "UtilityId": null,
      "CountyName": "Hendry",
      "CountyState": null,
      "CountyStatus": "#004FA2",
      "OutageCount": 0,
      "CustomerCount": 15077
    },
    {
      "CountyId": 313,
      "UtilityId": null,
      "CountyName": "Hernando",
      "CountyState": null,
      "CountyStatus": "#004FA2",
      "OutageCount": 0,
      "CustomerCount": 101839
    },
    {
      "CountyId": 314,
      "UtilityId": null,
      "CountyName": "Highlands",
      "CountyState": null,
      "CountyStatus": "#004FA2",
      "OutageCount": 0,
      "CustomerCount": 65690
    },
    {
      "CountyId": 315,
      "UtilityId": null,
      "CountyName": "Hillsborough",
      "CountyState": null,
      "CountyStatus": "#004FA2",
      "OutageCount": 0,
      "CustomerCount": 673529
    },
    {
      "CountyId": 316,
      "UtilityId": null,
      "CountyName": "Indian River",
      "CountyState": null,
      "CountyStatus": "#004FA2",
      "OutageCount": 0,
      "CustomerCount": 99936
    },
    {
      "CountyId": 317,
      "UtilityId": null,
      "CountyName": "Jefferson",
      "CountyState": null,
      "CountyStatus": "#004FA2",
      "OutageCount": 0,
      "CustomerCount": 8737
    },
    {
      "CountyId": 318,
      "UtilityId": null,
      "CountyName": "Lafayette",
      "CountyState": null,
      "CountyStatus": "#014FA1",
      "OutageCount": 2,
      "CustomerCount": 4380
    },
    {
      "CountyId": 319,
      "UtilityId": null,
      "CountyName": "Lake",
      "CountyState": null,
      "CountyStatus": "#004FA2",
      "OutageCount": 0,
      "CustomerCount": 171162
    },
    {
      "CountyId": 320,
      "UtilityId": null,
      "CountyName": "Lee",
      "CountyState": null,
      "CountyStatus": "#004FA2",
      "OutageCount": 0,
      "CustomerCount": 489318
    },
    {
      "CountyId": 321,
      "UtilityId": null,
      "CountyName": "Leon",
      "CountyState": null,
      "CountyStatus": "#004FA2",
      "OutageCount": 0,
      "CustomerCount": 131088
    },
    {
      "CountyId": 322,
      "UtilityId": null,
      "CountyName": "Levy",
      "CountyState": null,
      "CountyStatus": "#004FA2",
      "OutageCount": 0,
      "CustomerCount": 24854
    },
    {
      "CountyId": 323,
      "UtilityId": null,
      "CountyName": "Liberty",
      "CountyState": null,
      "CountyStatus": "#004FA2",
      "OutageCount": 0,
      "CustomerCount": 4186
    },
    {
      "CountyId": 324,
      "UtilityId": null,
      "CountyName": "Madison",
      "CountyState": null,
      "CountyStatus": "#004FA2",
      "OutageCount": 0,
      "CustomerCount": 11527
    },
    {
      "CountyId": 325,
      "UtilityId": null,
      "CountyName": "Manatee",
      "CountyState": null,
      "CountyStatus": "#004FA2",
      "OutageCount": 0,
      "CustomerCount": 236498
    },
    {
      "CountyId": 326,
      "UtilityId": null,
      "CountyName": "Marion",
      "CountyState": null,
      "CountyStatus": "#004FA2",
      "OutageCount": 0,
      "CustomerCount": 210268
    },
    {
      "CountyId": 327,
      "UtilityId": null,
      "CountyName": "Martin",
      "CountyState": null,
      "CountyStatus": "#004FA2",
      "OutageCount": 0,
      "CustomerCount": 94850
    },
    {
      "CountyId": 328,
      "UtilityId": null,
      "CountyName": "Miami-dade",
      "CountyState": null,
      "CountyStatus": "#004FA2",
      "OutageCount": 0,
      "CustomerCount": 1181360
    },
    {
      "CountyId": 329,
      "UtilityId": null,
      "CountyName": "Monroe",
      "CountyState": null,
      "CountyStatus": "#004FA2",
      "OutageCount": 0,
      "CustomerCount": 100158
    },
    {
      "CountyId": 330,
      "UtilityId": null,
      "CountyName": "Nassau",
      "CountyState": null,
      "CountyStatus": "#004FA2",
      "OutageCount": 1,
      "CustomerCount": 51271
    },
    {
      "CountyId": 331,
      "UtilityId": null,
      "CountyName": "Okeechobee",
      "CountyState": null,
      "CountyStatus": "#004FA2",
      "OutageCount": 0,
      "CustomerCount": 22943
    },
    {
      "CountyId": 332,
      "UtilityId": null,
      "CountyName": "Orange",
      "CountyState": null,
      "CountyStatus": "#004FA2",
      "OutageCount": 3,
      "CustomerCount": 635630
    },
    {
      "CountyId": 333,
      "UtilityId": null,
      "CountyName": "Osceola",
      "CountyState": null,
      "CountyStatus": "#004FA2",
      "OutageCount": 1,
      "CustomerCount": 201551
    },
    {
      "CountyId": 334,
      "UtilityId": null,
      "CountyName": "Palm Beach",
      "CountyState": null,
      "CountyStatus": "#004FA2",
      "OutageCount": 0,
      "CustomerCount": 767390
    },
    {
      "CountyId": 335,
      "UtilityId": null,
      "CountyName": "Pasco",
      "CountyState": null,
      "CountyStatus": "#004FA2",
      "OutageCount": 0,
      "CustomerCount": 305156
    },
    {
      "CountyId": 336,
      "UtilityId": null,
      "CountyName": "Pinellas",
      "CountyState": null,
      "CountyStatus": "#004FA2",
      "OutageCount": 0,
      "CustomerCount": 571663
    },
    {
      "CountyId": 337,
      "UtilityId": null,
      "CountyName": "Polk",
      "CountyState": null,
      "CountyStatus": "#004FA2",
      "OutageCount": 0,
      "CustomerCount": 357332
    },
    {
      "CountyId": 338,
      "UtilityId": null,
      "CountyName": "Putnam",
      "CountyState": null,
      "CountyStatus": "#004FA2",
      "OutageCount": 0,
      "CustomerCount": 42557
    },
    {
      "CountyId": 339,
      "UtilityId": null,
      "CountyName": "Sarasota",
      "CountyState": null,
      "CountyStatus": "#004FA2",
      "OutageCount": 0,
      "CustomerCount": 287418
    },
    {
      "CountyId": 340,
      "UtilityId": null,
      "CountyName": "Seminole",
      "CountyState": null,
      "CountyStatus": "#004FA2",
      "OutageCount": 0,
      "CustomerCount": 225537
    },
    {
      "CountyId": 342,
      "UtilityId": null,
      "CountyName": "St. Lucie",
      "CountyState": null,
      "CountyStatus": "#004FA2",
      "OutageCount": 0,
      "CustomerCount": 174759
    },
    {
      "CountyId": 343,
      "UtilityId": null,
      "CountyName": "Sumter",
      "CountyState": null,
      "CountyStatus": "#004FA2",
      "OutageCount": 0,
      "CustomerCount": 86090
    },
    {
      "CountyId": 344,
      "UtilityId": null,
      "CountyName": "Suwannee",
      "CountyState": null,
      "CountyStatus": "#004FA2",
      "OutageCount": 0,
      "CustomerCount": 24352
    },
    {
      "CountyId": 345,
      "UtilityId": null,
      "CountyName": "Taylor",
      "CountyState": null,
      "CountyStatus": "#004FA2",
      "OutageCount": 0,
      "CustomerCount": 13731
    },
    {
      "CountyId": 346,
      "UtilityId": null,
      "CountyName": "Union",
      "CountyState": null,
      "CountyStatus": "#004FA2",
      "OutageCount": 0,
      "CustomerCount": 5769
    },
    {
      "CountyId": 347,
      "UtilityId": null,
      "CountyName": "Unknown",
      "CountyState": null,
      "CountyStatus": "#004FA2",
      "OutageCount": 0,
      "CustomerCount": 14144
    },
    {
      "CountyId": 348,
      "UtilityId": null,
      "CountyName": "Volusia",
      "CountyState": null,
      "CountyStatus": "#004FA2",
      "OutageCount": 0,
      "CustomerCount": 310864
    },
    {
      "CountyId": 349,
      "UtilityId": null,
      "CountyName": "Wakulla",
      "CountyState": null,
      "CountyStatus": "#004FA2",
      "OutageCount": 0,
      "CustomerCount": 17555
    },
    {
      "CountyId": 2272,
      "UtilityId": null,
      "CountyName": "Escambia",
      "CountyState": null,
      "CountyStatus": "#004FA2",
      "OutageCount": 0,
      "CustomerCount": 156919
    },
    {
      "CountyId": 2273,
      "UtilityId": null,
      "CountyName": "Holmes",
      "CountyState": null,
      "CountyStatus": "#004FA2",
      "OutageCount": 0,
      "CustomerCount": 10636
    },
    {
      "CountyId": 2274,
      "UtilityId": null,
      "CountyName": "Jackson",
      "CountyState": null,
      "CountyStatus": "#004FA2",
      "OutageCount": 0,
      "CustomerCount": 25569
    },
    {
      "CountyId": 2275,
      "UtilityId": null,
      "CountyName": "Okaloosa",
      "CountyState": null,
      "CountyStatus": "#004FA2",
      "OutageCount": 0,
      "CustomerCount": 114991
    },
    {
      "CountyId": 2276,
      "UtilityId": null,
      "CountyName": "Santa Rosa",
      "CountyState": null,
      "CountyStatus": "#004FA2",
      "OutageCount": 0,
      "CustomerCount": 84763
    },
    {
      "CountyId": 2277,
      "UtilityId": null,
      "CountyName": "Walton",
      "CountyState": null,
      "CountyStatus": "#004FA2",
      "OutageCount": 0,
      "CustomerCount": 69414
    },
    {
      "CountyId": 2278,
      "UtilityId": null,
      "CountyName": "Washington",
      "CountyState": null,
      "CountyStatus": "#004FA2",
      "OutageCount": 0,
      "CustomerCount": 13271
    },
    {
      "CountyId": 2317,
      "UtilityId": null,
      "CountyName": "St. Johns",
      "CountyState": null,
      "CountyStatus": "#004FA2",
      "OutageCount": 30,
      "CustomerCount": 134536
    },
    {
      "CountyId": 2340,
      "UtilityId": null,
      "CountyName": "Desoto",
      "CountyState": null,
      "CountyStatus": "#004FA2",
      "OutageCount": 0,
      "CustomerCount": 18741
    },
    {
      "CountyId": 2343,
      "UtilityId": null,
      "CountyName": "Calhoun",
      "CountyState": null,
      "CountyStatus": "#004FA2",
      "OutageCount": 0,
      "CustomerCount": 5480
    }
  ]
}
